pyrom/__init__.py
pyrom/__main__.py
pyrom/args.py
pyrom/check.py
pyrom/console.py
pyrom/game.py
pyrom/hashes.py
pyrom/helpers.py
pyrom/morph.py
pyrom/parsing.py
pyrom/resolve.py
pyrom/stats.py
pyrom-1.0.data/data/share/man/man1/pyrom-morph.1
pyrom-1.0.data/data/share/man/man1/pyrom-resolve.1
pyrom-1.0.data/data/share/man/man1/pyrom.1
pyrom-1.0.dist-info/entry_points.txt
pyrom-1.0.dist-info/licenses/LICENSES/GPL-3.0-or-later.txt
pyrom-1.0.dist-info/WHEEL
pyrom-1.0.dist-info/METADATA
pyrom-1.0.dist-info/RECORD
