Metadata-Version: 2.4
Name: pyrom
Version: 1.0
Summary: A set of tools for managing your ROM collection and DATfiles
Author: 1corn2
Maintainer: 1corn2
Requires-Python: >=3.12
License-Expression: GPL-3.0-or-later
Classifier: Development Status :: 5 - Production/Stable
Classifier: Environment :: Console
Classifier: Intended Audience :: End Users/Desktop
Classifier: Natural Language :: English
Classifier: Operating System :: POSIX
Classifier: Programming Language :: Python :: 3.12
Classifier: Programming Language :: Python :: 3.13
Classifier: Topic :: Utilities
Classifier: Typing :: Typed
License-File: LICENSES/GPL-3.0-or-later.txt
Requires-Dist: rich>=13.9.4
Requires-Dist: blake3>=1.0.5 ; extra == "blake3"
Requires-Dist: lxml>=6.0.0 ; extra == "lxml"
Requires-Dist: xxhash>=3.5.0 ; extra == "xxhash"
Project-URL: GitHub, https://github.com/1corn2/PyRom
Project-URL: Homepage, https://github.com/1corn2/PyRom
Provides-Extra: blake3
Provides-Extra: lxml
Provides-Extra: xxhash
